{
  "name": "Loon Tao",
  "address": "43/12 College Avenue, Mount Lavinia.",
  "open_until": " Open 11 to 3- Afternoon\n 6 to 11 - Evenings",
  "telephone": "0112722723",
  "description": "Loon Tao, roughly meaning \"Way of the Dragon\" has lost its claim as a top contender in the Chinese restaurant racket. ",
  "reviews": "Loon Tao, roughly translating to \u2018The Way Of the Dragon\u2019 has always leaned towards slightly more authentic East Asian flavours. One of the few semi fine-dining Chinese restaurants in Sri Lanka the Tao chain promises slightly more authentic Chinese cuisine in an elegant setting. While their promise holds true, Loon Tao\u2019s claim as a top contender in the Chinese restaurant racket has waned drastically\nLoon Tao\u2019s flavours aren\u2019t typically Sri Lankan Chinese. They\u2019re more Chi-Lankan \u2013 comprising of the typical East Asian bite of pepper, garlic and fennel blended to fit the Sri Lankan palette.Up until now I have never had great qualms with their food. It\u2019s usually pretty good and is presented to please the olfactory, visual and gustatory.\nI opened ranks with their hokkien style fried noodle with seafood at Rs.598. These are thick noodles, covered in a heavy coating of sauce and seafood. The creaminess rendered from the sauce in addition to the thickness of the noodles makes for a satisfactory and filling main. However I was mildly disappointed by the prawns in the seafood mix. While they were large, they felt slightly underdone; not tender in the least, with a slight rubbery texture.  For a small portion the serving is actually fairly large- more than enough for two I\u2019d reckon.\nTo accompany the main I got Sri Lanka\u2019s favourite \u2013 A small portion of hot buttered cuttlefish (Rs.668), an unorthodox crispy deep fried beef (Rs.598) and pak choy (Rs. 498) . It\u2019s ridiculous how every price including mineral water (Rs.198) ends with the figure eight. Unlucky much?\nWhile it certainly isn't the best\nLoon Tao, roughly meaning 'Path Of the Dragon' seems to have steered heavily off course. They aren't what they used to be.\nHalf in an open-air beach shack, and the other half under the stars, Loon Tao serves delicious pan-Asian seafood on Mt. Lavinia beach, at a reasonable price. The restaurant\u2019s biggest culinary strength is the simplicity of its cuisine.\n\n\u0dbd\u0dd6\u0db1\u0dca \u0dad\u0dcf\u0dc0\u0ddd \u0d85\u0da9\u0d9a\u0dca, \u0dc0\u0dd2\u0dc0\u0dd8\u0dad \u0dc0\u0dd9\u0dbb\u0dc5 \u0d9a\u0dd4\u0da7\u0dd2\u0dba\u0d9a\u0dca. \u0d85\u0db1\u0dd9\u0d9a\u0dca \u0d85\u0da9 \u0dad\u0dbb\u0dd4 \u0dc0\u0dd2\u0db8\u0db1 \u0dba\u0da7. \u0dbd\u0dd6\u0db1\u0dca \u0dad\u0dcf\u0dc0\u0ddd \u0d9c\u0dbd\u0dca\u0d9a\u0dd2\u0dc3\u0dca\u0dc3 \u0dc0\u0dd9\u0dbb\u0dc5\u0dda \u0dc3\u0dcf\u0db0\u0dcf\u0dbb\u0dab \u0db8\u0dd2\u0dbd\u0d9a\u0da7 \u0dc3\u0dd2\u0dba\u0dc5\u0dd4\u0db8 \u0d86\u0dc3\u0dd2\u0dba\u0dcf\u0db1\u0dd4 \u0dc3\u0dd3 \u0dc6\u0dd4\u0da9\u0dca \u0d89\u0daf\u0dd2\u0dbb\u0dd2\u0db4\u0dad\u0dca \u0d9a\u0dbb\u0db1\u0dc0\u0dcf. \u0d85\u0dc0\u0db1\u0dca\u0dc4\u0dbd\u0dda \u0dad\u0dd2\u0dba\u0dd9\u0db1 \u0dc0\u0dd2\u0dc1\u0dda\u0dc2\u0dad\u0dca\u0dc0\u0dba \u0dad\u0db8\u0dba\u0dd2 \u0d86\u0dc4\u0dbb\u0dc0\u0dbd \u0d87\u0dad\u0dd2 \u0dc3\u0dbb\u0dbd\u0db6\u0dc0. \u0dad\u0daf\u0dd2\u0db1\u0dca\u0db8 \u0d86\u0dc3\u0dd2\u0dba\u0dcf\u0db1\u0dd4 \u0dbb\u0dc3\u0dc0\u0dbd\u0da7 \u0dc4\u0dd4\u0dbb\u0dd4\u0dc0\u0dd3 \u0d87\u0dad\u0dd2 \u0db8\u0dd9\u0db8 \u0d85\u0dc0\u0db1\u0dca\u0dc4\u0dbd\u0dda \u0d9a\u0ddc\u0dad\u0dca\u0dad\u0db8\u0dbd\u0dca\u0dbd\u0dd2, \u0db8\u0dd2\u0dbb\u0dd2\u0dc3\u0dca, \u0dc3\u0dd4\u0daf\u0dd4\u0dc5\u0dd6\u0db1\u0dd4, \u0db8\u0dc4\u0daf\u0dd4\u0dbb\u0dd4, \u0dad\u0dbd \u0dad\u0dd9\u0dbd\u0dca, \u0daf\u0dd9\u0dc4\u0dd2 \u0dc4\u0dcf \u0d9c\u0db8\u0dca\u0db8\u0dd2\u0dbb\u0dd2\u0dc3\u0dca \u0dc0\u0dbb\u0dca\u0d9c \u0d9c\u0db1\u0dab\u0dcf\u0dc0\u0d9a\u0dca \u0dc4\u0dbb\u0dd2 \u0db4\u0daf\u0db8\u0da7 \u0daf\u0dd0\u0db8\u0dd6 \u0d86\u0dc4\u0dcf\u0dbb \u0dc0\u0dbb\u0daf\u0dd2\u0db1\u0dca\u0db1\u0dd9\u0db8 \u0db1\u0dd0\u0dc4\u0dd0.\n",
  "yamu_rating": "It's alright",
  "url": "https://www.yamu.lk/place/loon-tao/review-48466",
  "img_urls": [
    "https://d3dz4rogqkqh6r.cloudfront.net/uploads/files/2018/06/yimg_oarYI3.jpg",
    "https://d3dz4rogqkqh6r.cloudfront.net/uploads/files/2018/01/yimg_iCGWqc.png",
    "https://www.yamu.lk/l/assets/img/fork.svg",
    "https://www.yamu.lk/l/assets/img/culture.svg",
    "https://www.yamu.lk/l/assets/img/yamu_logo.svg",
    "https://d3dz4rogqkqh6r.cloudfront.net/uploads/files/2018/06/yimg_amrU6R.jpg",
    "https://www.yamu.lk/uploads/files/2015/06/yimg_02pm9f-150x100.jpg",
    "https://www.yamu.lk/uploads/files/2015/06/yimg_ZxKIkG-150x100.jpg",
    "https://www.yamu.lk/uploads/files/2015/06/yimg_iF8Dat-150x100.jpg",
    "https://www.yamu.lk/uploads/files/2015/06/yimg_8oOOlz-150x100.jpg",
    "https://www.yamu.lk/wp-content/uploads/2013/05/20130714_2020191-150x105.jpg",
    "https://www.yamu.lk/wp-content/uploads/2013/05/20130714_2021111-150x105.jpg",
    "https://www.yamu.lk/wp-content/uploads/2013/05/20130714_2023241-150x105.jpg",
    "https://www.yamu.lk/wp-content/uploads/2013/05/20130714_2023311-150x105.jpg",
    "https://www.yamu.lk/uploads/dp/2015/07/r7ukSszy258MtvRTun.jpg",
    "https://www.yamu.lk/uploads/files/2015/06/yimg_02pm9f-640x450.jpg",
    "https://www.yamu.lk/uploads/files/2015/06/yimg_iF8Dat-640x413.jpg",
    "https://www.yamu.lk/uploads/files/2015/06/yimg_ZxKIkG-640x619.jpg",
    "https://www.yamu.lk/uploads/files/2015/06/yimg_8oOOlz-640x515.jpg",
    "https://www.yamu.lk/wp-content/uploads/2013/05/20130714_2020191-600x337.jpg",
    "https://d3dz4rogqkqh6r.cloudfront.net/uploads/files/2017/03/yimg_DWnStO.png",
    "https://d3dz4rogqkqh6r.cloudfront.net/uploads/files/2016/09/yimg_L4Ylap-600x250.jpg",
    "https://d3dz4rogqkqh6r.cloudfront.net/uploads/files/2016/10/yimg_mOENRl-600x250.jpg",
    "https://www.yamu.lk/uploads/dp/2015/07/r7ukSszy258MtvRTun.jpg",
    "https://d3dz4rogqkqh6r.cloudfront.net/uploads/files/2018/03/yimg_V9gegf.jpg",
    "https://www.yamu.lk/uploads/files/2015/06/yimg_02pm9f-640x450.jpg",
    "https://www.yamu.lk/uploads/files/2015/06/yimg_ZxKIkG-640x619.jpg",
    "https://www.yamu.lk/uploads/files/2015/06/yimg_iF8Dat-640x413.jpg",
    "https://www.yamu.lk/uploads/files/2015/06/yimg_8oOOlz-640x515.jpg",
    "https://d3dz4rogqkqh6r.cloudfront.net/uploads/files/2018/01/yimg_sl08gd.gif",
    "https://www.facebook.com/tr?id=609408732574388&ev=PageView&noscript=1"
  ]
}